CHANGES.txt
CONTRIBUTORS.txt
LICENSE
MANIFEST.in
README.txt
setup.cfg
setup.py
pbp/__init__.py
pbp.recipe.trac.egg-info/PKG-INFO
pbp.recipe.trac.egg-info/SOURCES.txt
pbp.recipe.trac.egg-info/dependency_links.txt
pbp.recipe.trac.egg-info/entry_points.txt
pbp.recipe.trac.egg-info/namespace_packages.txt
pbp.recipe.trac.egg-info/not-zip-safe
pbp.recipe.trac.egg-info/requires.txt
pbp.recipe.trac.egg-info/top_level.txt
pbp/recipe/__init__.py
pbp/recipe/trac/README.txt
pbp/recipe/trac/__init__.py
pbp/recipe/trac/tests/__init__.py
pbp/recipe/trac/tests/test_docs.py