Metadata-Version: 1.0
Name: pbp.recipe.trac
Version: 0.4.0
Summary: ZC Buildout recipe to install and configure a Trac server.
Home-page: http://pypi.python.org/pypi/pbp.recipe.trac
Author: Tarek Ziade
Author-email: tarek@ziade.org
License: GPL
Keywords: trac pbp buildout recipe
Platform: UNKNOWN
Classifier: Framework :: Buildout
Classifier: Framework :: Trac
Classifier: Intended Audience :: Developers
Classifier: Topic :: Software Development :: Build Tools
Classifier: Topic :: Software Development :: Libraries :: Python Modules
Classifier: License :: OSI Approved :: GNU General Public License (GPL)
